{"duration":165,"badge":"hard","assist":70,"ease":2,"segmentationOverrides":[{"skill":"group1","time":1.29999995231628},{"skill":"group2","time":1.08000004291534},{"skill":"group3","time":0.850000023841858},{"skill":"group4","time":0.699999988079071},{"skill":"group5","time":0.550000011920929}],"goals":[[{"id":"cup3","count":5}],[{"id":"airplane3","count":7}]],"board":[{"id":"donut","count":15},{"id":"fish","count":20},{"id":"star","count":20},{"id":"frog","count":20},{"id":"cup2","count":5,"modifier":"spammer"},{"id":"airplane","count":5,"modifier":"spammer"},{"id":"chair3","count":15},{"id":"balloon","count":15},{"id":"cupCake","count":15}]}